survex3dreader/__init__.py
survex3dreader/reader.py
survex3dreader-0.0.1.dist-info/METADATA
survex3dreader-0.0.1.dist-info/WHEEL
survex3dreader-0.0.1.dist-info/top_level.txt
survex3dreader-0.0.1.dist-info/RECORD
