Metadata-Version: 2.1
Name: survex3dreader
Version: 0.0.1
Summary: Reader for Survex 3d files .3d
Home-page: https://github.com/RadostW/survex-3d-reader
Author: Radost Waszkiewicz
Author-email: radost.waszkiewicz@gmail.com
License: GPL 2.0
Project-URL: Source, https://github.com/RadostW/survex-3d-reader
